{
  "BASE_GENERATOR": [
    {
      "lib": "GeneratorFictitious"
    }
  ],
  "SYNCHRONOUS_GENERATOR": [
    {
      "lib": "GeneratorSynchronousFourWindings"
    },
    {
      "lib": "GeneratorSynchronousFourWindingsGoverPropVRPropInt",
      "properties": [
        "Controllable"
      ]
    },
    {
      "lib": "GeneratorSynchronousFourWindingsGovSteam1ExcIEEEST4B"
    },
    {
      "lib": "GeneratorSynchronousFourWindingsGovSteam1ExcIEEEST4BPssIEEE2B"
    },
    {
      "lib": "GeneratorSynchronousFourWindingsPmConstVRNordic"
    },
    {
      "lib": "GeneratorSynchronousFourWindingsPmConstVRNordicTfo",
      "properties": [
        "Transformer"
      ]
    },
    {
      "lib": "GeneratorSynchronousFourWindingsProportionalRegulations",
      "properties": [
        "Controllable"
      ]
    },
    {
      "lib": "GeneratorSynchronousFourWindingsTGov1Sexs"
    },
    {
      "lib": "GeneratorSynchronousFourWindingsTGov1SexsPss2A"
    },
    {
      "lib": "GeneratorSynchronousFourWindingsVRKundur"
    },
    {
      "lib": "GeneratorSynchronousFourWindingsVRKundurPssKundur"
    },
    {
      "lib": "GeneratorSynchronousProportionalRegulationsInternalParameters"
    },
    {
      "lib": "GeneratorSynchronousThreeWindings"
    },
    {
      "lib": "GeneratorSynchronousThreeWindingsGoverNordicVRNordic"
    },
    {
      "lib": "GeneratorSynchronousThreeWindingsGoverNordicVRNordicTfo",
      "properties": [
        "Transformer"
      ]
    },
    {
      "lib": "GeneratorSynchronousThreeWindingsGoverPropVRPropInt",
      "properties": [
        "Controllable"
      ]
    },
    {
      "lib": "GeneratorSynchronousThreeWindingsPmConstVRNordic"
    },
    {
      "lib": "GeneratorSynchronousThreeWindingsPmConstVRNordicTfo",
      "properties": [
        "Transformer"
      ]
    },
    {
      "lib": "GeneratorSynchronousThreeWindingsProportionalRegulations",
      "properties": [
        "Controllable"
      ]
    }
  ],
  "SYNCHRONIZED_GENERATOR": [
    {
      "lib": "GeneratorPQ"
    },
    {
      "lib": "GeneratorPV",
      "properties": [
        "Controllable"
      ]
    },
    {
      "lib": "GeneratorPVFixed"
    },
    {
      "lib": "GeneratorPVDiagramPQ"
    }
  ],
  "HVDC_P": [
    {
      "lib": "HvdcPV"
    },
    {
      "lib": "HvdcPVEmulation"
    },
    {
      "lib": "HvdcPVEmulationSet"
    },
    {
      "lib": "HvdcPVDiagramPQ"
    },
    {
      "lib": "HvdcPVDiagramPQEmulation"
    },
    {
      "lib": "HvdcPVDiagramPQEmulationSet"
    },
    {
      "lib": "HvdcPTanPhi"
    },
    {
      "lib": "HvdcPTanPhiDiagramPQ"
    },
    {
      "lib": "HvdcPVDangling",
      "properties": [
        "Dangling"
      ]
    },
    {
      "lib": "HvdcPVDanglingDiagramPQ",
      "properties": [
        "Dangling"
      ]
    },
    {
      "lib": "HvdcPTanPhiDangling",
      "properties": [
        "Dangling"
      ]
    },
    {
      "lib": "HvdcPTanPhiDanglingDiagramPQ",
      "properties": [
        "Dangling"
      ]
    }
  ],
  "HVDC_VSC": [
    {
      "lib": "HvdcVSC"
    },
    {
      "lib": "HvdcVSCEmulation"
    },
    {
      "lib": "HvdcVSCDanglingP",
      "properties": [
        "Dangling"
      ]
    },
    {
      "lib": "HvdcVSCDanglingUdc",
      "properties": [
        "Dangling"
      ]
    }
  ],
  "BASE_BUS": [
    {
      "lib": "Bus"
    }
  ],
  "INFINITE_BUS": [
    {
      "lib": "InfiniteBus"
    },
    {
      "lib": "InfiniteBusWithImpedance"
    },
    {
      "lib": "InfiniteBusWithVariations"
    }
  ],
  "BASE_LOAD": [
    {
      "lib": "LoadAlphaBeta",
      "properties": [
        "Controllable"
      ]
    },
    {
      "lib": "LoadAlphaBetaRestorative"
    },
    {
      "lib": "LoadAlphaBetaRestorativeLimitsRecalc"
    },
    {
      "lib": "LoadAlphaBetaMotor"
    },
    {
      "lib": "LoadPQ"
    }
  ],
  "LOAD_ONE_TRANSFORMER": [
    {
      "lib": "LoadOneTransformer"
    }
  ],
  "LOAD_ONE_TRANSFORMER_TAP_CHANGER": [
    {
      "lib": "LoadOneTransformerTapChanger"
    }
  ],
  "LOAD_TWO_TRANSFORMERS": [
    {
      "lib": "LoadTwoTransformers"
    }
  ],
  "LOAD_TWO_TRANSFORMERS_TAP_CHANGER": [
    {
      "lib": "LoadTwoTransformersTapChangers"
    }
  ],
  "BASE_LINE": [
    {
      "lib": "Line"
    }
  ],
  "BASE_STATIC_VAR_COMPENSATOR": [
    {
      "lib": "StaticVarCompensator"
    },
    {
      "lib": "StaticVarCompensatorPV"
    },
    {
      "lib": "StaticVarCompensatorPVModeHandling"
    },
    {
      "lib": "StaticVarCompensatorPVRemote"
    },
    {
      "lib": "StaticVarCompensatorPVRemoteModeHandling"
    },
    {
      "lib": "StaticVarCompensatorPVProp"
    },
    {
      "lib": "StaticVarCompensatorPVPropModeHandling"
    },
    {
      "lib": "StaticVarCompensatorPVPropRemote"
    },
    {
      "lib": "StaticVarCompensatorPVPropRemoteModeHandling"
    }
  ],
  "TRANSFORMER": [
    {
      "lib": "TransformerFixedRatio"
    }
  ],
  "WECC": [
    {
      "lib": "WTG4AWeccCurrentSource",
      "internalModelPrefix": "WTG4A",
      "properties": [
        "Synchronized"
      ]
    },
    {
      "lib": "WTG4BWeccCurrentSource",
      "internalModelPrefix": "WTG4B",
      "properties": [
        "Synchronized"
      ]
    },
    {
      "lib": "WT4AWeccCurrentSource",
      "internalModelPrefix": "WT4A"
    },
    {
      "lib": "WT4BWeccCurrentSource",
      "internalModelPrefix": "WT4B"
    },
    {
      "lib": "PhotovoltaicsWeccCurrentSource",
      "internalModelPrefix": "photovoltaics",
      "properties": [
        "Synchronized"
      ]
    },
    {
      "lib": "PhotovoltaicsWeccVoltageSource",
      "internalModelPrefix": "photovoltaics",
      "properties": [
        "Synchronized"
      ]
    }
  ],
  "GRID_FORMING_CONVERTER": [
    {
      "lib": "GridFormingConverterDroopControl",
      "properties": [
        "Synchronized"
      ]
    },
    {
      "lib": "GridFormingConverterMatchingControl",
      "properties": [
        "Synchronized"
      ]
    },
    {
      "lib": "GridFormingConverterDispatchableVirtualOscillatorControl",
      "properties": [
        "Synchronized"
      ]
    }
  ],
  "CLA": [
    {
      "lib": "CurrentLimitAutomaton"
    }
  ],
  "CLA_TWO_LEVElS": [
    {
      "lib": "CurrentLimitAutomatonTwoLevels"
    }
  ],
  "PHASE_SHIFTER_I": [
    {
      "lib": "PhaseShifterI"
    }
  ],
  "PHASE_SHIFTER_P": [
    {
      "lib": "PhaseShifterP"
    }
  ],
  "TAP_CHANGER": [
    {
      "lib": "TapChangerAutomaton"
    }
  ],
  "TCB": [
    {
      "lib": "TapChangerBlockingAutomaton"
    }
  ],
  "UNDER_VOLTAGE": [
    {
      "lib": "UnderVoltageAutomaton",
      "alias": "UnderVoltage"
    }
  ]
}